pyelib/__init__.py
pyelib/azure.py
pyelib/mongdb.py
pyelib-0.0.5.dist-info/LICENSE
pyelib-0.0.5.dist-info/METADATA
pyelib-0.0.5.dist-info/WHEEL
pyelib-0.0.5.dist-info/top_level.txt
pyelib-0.0.5.dist-info/RECORD
