Metadata-Version: 2.1
Name: pyelib
Version: 0.0.5
Summary: pyelib是一个Python库，为标准库和第三方库提供易于使用的函数封装。
Home-page: https://github.com/xuehangcang/pyelib
Author: Xuehang Cang
Author-email: xuehangcang@outlook.com
Keywords: pymongo
Classifier: Programming Language :: Python :: 3
Classifier: Operating System :: Unix
Classifier: Operating System :: MacOS :: MacOS X
Classifier: Operating System :: Microsoft :: Windows
License-File: LICENSE
Requires-Dist: pymongo
Requires-Dist: openai
